sconstool/bennugd/__init__.py
sconstool/bennugd/dcbc.py
scons_tool_bennugd-1.0.1.dist-info/LICENSE
scons_tool_bennugd-1.0.1.dist-info/METADATA
scons_tool_bennugd-1.0.1.dist-info/WHEEL
scons_tool_bennugd-1.0.1.dist-info/top_level.txt
scons_tool_bennugd-1.0.1.dist-info/RECORD
