Metadata-Version: 2.1
Name: scons-tool-bennugd
Version: 1.0.1
Summary: SCons tool to build BennuGD project
Home-page: https://bitbucket.org/dacucar/scons-tool-bennugd
Author: Darío Cutillas Carrillo
Author-email: git@dario.nu
License: UNKNOWN
Platform: UNKNOWN
Classifier: Programming Language :: Python :: 3
Classifier: License :: OSI Approved :: MIT License
Classifier: Operating System :: OS Independent
License-File: LICENSE
